odoo8_addon_stock_dropshipping_dual_invoice-8.0.0.1.0.99.dev30-py3.8-nspkg.pth
odoo_addons/stock_dropshipping_dual_invoice/README.rst
odoo_addons/stock_dropshipping_dual_invoice/__init__.py
odoo_addons/stock_dropshipping_dual_invoice/__openerp__.py
odoo_addons/stock_dropshipping_dual_invoice/i18n/ca.po
odoo_addons/stock_dropshipping_dual_invoice/i18n/de.po
odoo_addons/stock_dropshipping_dual_invoice/i18n/es.po
odoo_addons/stock_dropshipping_dual_invoice/i18n/es_AR.po
odoo_addons/stock_dropshipping_dual_invoice/i18n/es_MX.po
odoo_addons/stock_dropshipping_dual_invoice/i18n/fi.po
odoo_addons/stock_dropshipping_dual_invoice/i18n/fr.po
odoo_addons/stock_dropshipping_dual_invoice/i18n/fr_FR.po
odoo_addons/stock_dropshipping_dual_invoice/i18n/hr.po
odoo_addons/stock_dropshipping_dual_invoice/i18n/it.po
odoo_addons/stock_dropshipping_dual_invoice/i18n/nl.po
odoo_addons/stock_dropshipping_dual_invoice/i18n/pt.po
odoo_addons/stock_dropshipping_dual_invoice/i18n/pt_BR.po
odoo_addons/stock_dropshipping_dual_invoice/i18n/pt_PT.po
odoo_addons/stock_dropshipping_dual_invoice/i18n/ro.po
odoo_addons/stock_dropshipping_dual_invoice/i18n/ru.po
odoo_addons/stock_dropshipping_dual_invoice/i18n/sl.po
odoo_addons/stock_dropshipping_dual_invoice/i18n/stock_dropshipping_dual_invoice.pot
odoo_addons/stock_dropshipping_dual_invoice/i18n/tr.po
odoo_addons/stock_dropshipping_dual_invoice/i18n/tr_TR.po
odoo_addons/stock_dropshipping_dual_invoice/i18n/zh_CN.po
odoo_addons/stock_dropshipping_dual_invoice/model/__init__.py
odoo_addons/stock_dropshipping_dual_invoice/model/move.py
odoo_addons/stock_dropshipping_dual_invoice/model/picking.py
odoo_addons/stock_dropshipping_dual_invoice/model/purchase_order.py
odoo_addons/stock_dropshipping_dual_invoice/security/group.xml
odoo_addons/stock_dropshipping_dual_invoice/static/description/icon.png
odoo_addons/stock_dropshipping_dual_invoice/tests/__init__.py
odoo_addons/stock_dropshipping_dual_invoice/tests/test_get_journal_type.py
odoo8_addon_stock_dropshipping_dual_invoice-8.0.0.1.0.99.dev30.dist-info/METADATA
odoo8_addon_stock_dropshipping_dual_invoice-8.0.0.1.0.99.dev30.dist-info/WHEEL
odoo8_addon_stock_dropshipping_dual_invoice-8.0.0.1.0.99.dev30.dist-info/namespace_packages.txt
odoo8_addon_stock_dropshipping_dual_invoice-8.0.0.1.0.99.dev30.dist-info/top_level.txt
odoo8_addon_stock_dropshipping_dual_invoice-8.0.0.1.0.99.dev30.dist-info/RECORD
